goldenretriever/__init__.py
goldenretriever/__main__.py
goldenretriever/version.py
goldenretriever/callbacks/__init__.py
goldenretriever/callbacks/base.py
goldenretriever/callbacks/evaluation_callbacks.py
goldenretriever/callbacks/prediction_callbacks.py
goldenretriever/callbacks/training_callbacks.py
goldenretriever/callbacks/utils_callbacks.py
goldenretriever/cli/__init__.py
goldenretriever/cli/cli.py
goldenretriever/cli/utils.py
goldenretriever/common/__init__.py
goldenretriever/common/data_utils.py
goldenretriever/common/dist_utils.py
goldenretriever/common/from_config.py
goldenretriever/common/hf_utils.py
goldenretriever/common/log.py
goldenretriever/common/model_inputs.py
goldenretriever/common/sampler.py
goldenretriever/common/torch_utils.py
goldenretriever/common/upload.py
goldenretriever/common/utils.py
goldenretriever/data/__init__.py
goldenretriever/data/datasets.py
goldenretriever/data/labels.py
goldenretriever/data/utils.py
goldenretriever/data/base/__init__.py
goldenretriever/data/base/datasets.py
goldenretriever/indexers/__init__.py
goldenretriever/indexers/base.py
goldenretriever/indexers/document.py
goldenretriever/indexers/faiss.py
goldenretriever/indexers/inmemory.py
goldenretriever/lightning_modules/__init__.py
goldenretriever/lightning_modules/pl_data_modules.py
goldenretriever/lightning_modules/pl_modules.py
goldenretriever/pytorch_modules/__init__.py
goldenretriever/pytorch_modules/hf.py
goldenretriever/pytorch_modules/loss.py
goldenretriever/pytorch_modules/model.py
goldenretriever/pytorch_modules/modules.py
goldenretriever/pytorch_modules/optim.py
goldenretriever/pytorch_modules/scheduler.py
goldenretriever/serve/__init__.py
goldenretriever/serve/data/__init__.py
goldenretriever/serve/data/objects.py
goldenretriever/serve/data/splitters/__init__.py
goldenretriever/serve/data/splitters/base_sentence_splitter.py
goldenretriever/serve/data/splitters/spacy_sentence_splitter.py
goldenretriever/serve/data/splitters/window_based_splitter.py
goldenretriever_core-1.0.0.dist-info/METADATA
goldenretriever_core-1.0.0.dist-info/WHEEL
goldenretriever_core-1.0.0.dist-info/entry_points.txt
goldenretriever_core-1.0.0.dist-info/top_level.txt
goldenretriever_core-1.0.0.dist-info/RECORD
