Metadata-Version: 2.1
Name: goldenretriever-core
Version: 1.0.0
Summary: Dense Retriever
Home-page: https://github.com/Riccorl/golden-retriever
Author: Riccardo Orlando
Author-email: orlandorcc@gmail.com
License: Apache
Keywords: NLP deep learning transformer pytorch retriever rag dpr
Classifier: Intended Audience :: Science/Research
Classifier: License :: OSI Approved :: Apache Software License
Classifier: Programming Language :: Python :: 3
Classifier: Topic :: Scientific/Engineering :: Artificial Intelligence
Requires-Python: >=3.10
Requires-Dist: torch <2.4,>=2.3
Requires-Dist: transformers <4.42,>=4.41
Requires-Dist: datasets <2.20,>=2.19
Requires-Dist: rich <14.0.0,>=13.0.0
Requires-Dist: scikit-learn <1.5,>=1.3
Requires-Dist: typer <0.13,>=0.12
Requires-Dist: mosaicml <0.23,>=0.22
Requires-Dist: lightning <2.4,>=2.2
Requires-Dist: mosaicml-streaming <0.8,>=0.7.5
Requires-Dist: hydra-core <1.4,>=1.3
Requires-Dist: hydra-colorlog
Requires-Dist: wandb <0.17,>=0.16
Requires-Dist: art ==6.1
Requires-Dist: pprintpp ==0.4.0
Requires-Dist: colorama ==0.4.6
Provides-Extra: all
Requires-Dist: faiss-cpu ==1.8.0 ; extra == 'all'
Requires-Dist: optimum[onnxruntime] <1.17,>=1.14 ; extra == 'all'
Requires-Dist: termcolor <2.5,>=2.3 ; extra == 'all'
Requires-Dist: fastapi <0.110,>=0.104 ; extra == 'all'
Requires-Dist: uvicorn[standard] <0.28,>=0.24 ; extra == 'all'
Requires-Dist: gunicorn ==21.2.0 ; extra == 'all'
Requires-Dist: ray[serve] <=2.10,>=2.8 ; extra == 'all'
Requires-Dist: pre-commit ; extra == 'all'
Requires-Dist: black[d] ; extra == 'all'
Requires-Dist: isort ; extra == 'all'
Provides-Extra: all-gpu
Requires-Dist: termcolor <2.5,>=2.3 ; extra == 'all-gpu'
Requires-Dist: optimum[onnxruntime-gpu] <1.8,>=1.7 ; (platform_system == "Linux") and extra == 'all-gpu'
Provides-Extra: dev
Requires-Dist: pre-commit ; extra == 'dev'
Requires-Dist: black[d] ; extra == 'dev'
Requires-Dist: isort ; extra == 'dev'
Provides-Extra: faiss
Requires-Dist: faiss-cpu ==1.8.0 ; extra == 'faiss'
Provides-Extra: onnx
Requires-Dist: optimum[onnxruntime] <1.17,>=1.14 ; extra == 'onnx'
Requires-Dist: termcolor <2.5,>=2.3 ; extra == 'onnx'
Provides-Extra: onnx-gpu
Requires-Dist: termcolor <2.5,>=2.3 ; extra == 'onnx-gpu'
Requires-Dist: optimum[onnxruntime-gpu] <1.8,>=1.7 ; (platform_system == "Linux") and extra == 'onnx-gpu'
Provides-Extra: serve
Requires-Dist: fastapi <0.110,>=0.104 ; extra == 'serve'
Requires-Dist: uvicorn[standard] <0.28,>=0.24 ; extra == 'serve'
Requires-Dist: gunicorn ==21.2.0 ; extra == 'serve'
Requires-Dist: ray[serve] <=2.10,>=2.8 ; extra == 'serve'
